sharedbox/__init__.py
sharedbox/_shareddict.cp311-win_amd64.pyd
sharedbox/_shareddict.pyi
sharedbox/_shareddict.pyx
sharedbox/_version.py
sharedbox/utils.cp311-win_amd64.pyd
sharedbox/utils.py
sharedbox-0.1.0.dist-info/licenses/LICENSE
sharedbox-0.1.0.dist-info/METADATA
sharedbox-0.1.0.dist-info/WHEEL
sharedbox-0.1.0.dist-info/top_level.txt
sharedbox-0.1.0.dist-info/RECORD
